{
  "type": "FeatureCollection",
  "features": [
    {
      "type": "Feature",
      "geometry": {
        "type": "Point",
        "coordinates": [
          2.3522,
          48.8566
        ]
      },
      "properties": {
        "name": "WP1 Paris",
        "alt": 5000
      }
    },
    {
      "type": "Feature",
      "geometry": {
        "type": "Point",
        "coordinates": [
          5.3698,
          43.2965
        ]
      },
      "properties": {
        "name": "WP2 Marseille",
        "alt": 5200
      }
    },
    {
      "type": "Feature",
      "geometry": {
        "type": "Point",
        "coordinates": [
          7.2619,
          43.7102
        ]
      },
      "properties": {
        "name": "WP3 Nice",
        "alt": 4800
      }
    },
    {
      "type": "Feature",
      "geometry": {
        "type": "Point",
        "coordinates": [
          8.6821,
          50.1109
        ]
      },
      "properties": {
        "name": "WP4 Frankfurt",
        "alt": 6000
      }
    }
  ]
}