{
  "type": "FeatureCollection",
  "features": [
    {
      "type": "Feature",
      "geometry": {
        "type": "Point",
        "coordinates": [
          -1.25448,
          51.06739,
          408.7
        ]
      },
      "properties": {
        "code": "SYN01",
        "name": "Synthetic Airfield 01"
      }
    },
    {
      "type": "Feature",
      "geometry": {
        "type": "Point",
        "coordinates": [
          10.21421,
          37.55024,
          358.1
        ]
      },
      "properties": {
        "code": "SYN02",
        "name": "Synthetic Airfield 02"
      }
    },
    {
      "type": "Feature",
      "geometry": {
        "type": "Point",
        "coordinates": [
          -8.93856,
          43.05065,
          189.9
        ]
      },
      "properties": {
        "code": "SYN03",
        "name": "Synthetic Airfield 03"
      }
    },
    {
      "type": "Feature",
      "geometry": {
        "type": "Point",
        "coordinates": [
          -2.04649,
          41.91064,
          103.1
        ]
      },
      "properties": {
        "code": "SYN04",
        "name": "Synthetic Airfield 04"
      }
    },
    {
      "type": "Feature",
      "geometry": {
        "type": "Point",
        "coordinates": [
          15.99538,
          53.20237,
          479.9
        ]
      },
      "properties": {
        "code": "SYN05",
        "name": "Synthetic Airfield 05"
      }
    },
    {
      "type": "Feature",
      "geometry": {
        "type": "Point",
        "coordinates": [
          11.79766,
          51.88739,
          188.2
        ]
      },
      "properties": {
        "code": "SYN06",
        "name": "Synthetic Airfield 06"
      }
    },
    {
      "type": "Feature",
      "geometry": {
        "type": "Point",
        "coordinates": [
          -1.18238,
          56.62795,
          73.6
        ]
      },
      "properties": {
        "code": "SYN07",
        "name": "Synthetic Airfield 07"
      }
    },
    {
      "type": "Feature",
      "geometry": {
        "type": "Point",
        "coordinates": [
          13.57063,
          38.91265,
          75.5
        ]
      },
      "properties": {
        "code": "SYN08",
        "name": "Synthetic Airfield 08"
      }
    },
    {
      "type": "Feature",
      "geometry": {
        "type": "Point",
        "coordinates": [
          22.37722,
          46.28228,
          428.3
        ]
      },
      "properties": {
        "code": "SYN09",
        "name": "Synthetic Airfield 09"
      }
    },
    {
      "type": "Feature",
      "geometry": {
        "type": "Point",
        "coordinates": [
          -9.74005,
          37.65554,
          313.8
        ]
      },
      "properties": {
        "code": "SYN10",
        "name": "Synthetic Airfield 10"
      }
    }
  ]
}